{"frameRate":24,"name":"Skeleton2","version":"5.5","compatibleVersion":"5.5","armature":[{"type":"Sheet","frameRate":8,"name":"Idle","aabb":{"x":-32,"y":-32,"width":64,"height":64},"bone":[{"name":"root"}],"slot":[{"name":"sheetSlot","parent":"root"}],"skin":[{"slot":[{"name":"sheetSlot","display":[{"name":"idel01"},{"name":"idel02"},{"name":"idel03"},{"name":"idel04"}]}]}],"animation":[{"duration":4,"playTimes":0,"name":"Idle","slot":[{"name":"sheetSlot","displayFrame":[{},{"value":1},{"value":2},{"value":3}]}]}],"defaultActions":[{"gotoAndPlay":"Idle"}]},{"type":"Sheet","frameRate":12,"name":"Run","aabb":{"x":-32,"y":-32,"width":64,"height":64},"bone":[{"name":"root"}],"slot":[{"name":"sheetSlot","parent":"root"}],"skin":[{"slot":[{"name":"sheetSlot","display":[{"name":"run01"},{"name":"run02"},{"name":"run03"},{"name":"run04"},{"name":"run05"},{"name":"run06"},{"name":"run07"},{"name":"run08"},{"name":"run09"},{"name":"run10"},{"name":"run11"},{"name":"run12"}]}]}],"animation":[{"duration":12,"playTimes":0,"name":"Run","slot":[{"name":"sheetSlot","displayFrame":[{},{"value":1},{"value":2},{"value":3},{"value":4},{"value":5},{"value":6},{"value":7},{"value":8},{"value":9},{"value":10},{"value":11}]}]}],"defaultActions":[{"gotoAndPlay":"Run"}]},{"type":"Sheet","frameRate":6,"name":"TakeDamage","aabb":{"x":-32,"y":-32,"width":64,"height":64},"bone":[{"name":"root"}],"slot":[{"name":"sheetSlot","parent":"root"}],"skin":[{"slot":[{"name":"sheetSlot","display":[{"name":"hit01"},{"name":"hit02"},{"name":"hit03"}]}]}],"animation":[{"duration":3,"playTimes":0,"name":"TakeDamage","slot":[{"name":"sheetSlot","displayFrame":[{},{"value":1},{"value":2}]}]}],"defaultActions":[{"gotoAndPlay":"TakeDamage"}]},{"type":"Sheet","frameRate":12,"name":"Attack1","aabb":{"x":-32,"y":-32,"width":64,"height":64},"bone":[{"name":"root"}],"slot":[{"name":"sheetSlot","parent":"root"}],"skin":[{"slot":[{"name":"sheetSlot","display":[{"name":"attack01"},{"name":"attack02"},{"name":"attack03"},{"name":"attack04"},{"name":"attack05"},{"name":"attack06"},{"name":"attack07"},{"name":"attack08"},{"name":"attack09"},{"name":"attack10"},{"name":"attack11"},{"name":"attack12"},{"name":"attack13"}]}]}],"animation":[{"duration":13,"playTimes":0,"name":"Attack1","slot":[{"name":"sheetSlot","displayFrame":[{},{"value":1},{"value":2},{"value":3},{"value":4},{"value":5},{"value":6},{"value":7},{"value":8},{"value":9},{"value":10},{"value":11},{"value":12}]}]}],"defaultActions":[{"gotoAndPlay":"Attack1"}]},{"type":"Sheet","frameRate":12,"name":"Death","aabb":{"x":-32,"y":-32,"width":64,"height":64},"bone":[{"name":"root"}],"slot":[{"name":"sheetSlot","parent":"root"}],"skin":[{"slot":[{"name":"sheetSlot","display":[{"name":"death01"},{"name":"death02"},{"name":"death03"},{"name":"death04"},{"name":"death05"},{"name":"death06"},{"name":"death07"},{"name":"death08"},{"name":"death09"},{"name":"death10"},{"name":"death11"},{"name":"death12"},{"name":"death13"}]}]}],"animation":[{"duration":13,"playTimes":0,"name":"Death","slot":[{"name":"sheetSlot","displayFrame":[{},{"value":1},{"value":2},{"value":3},{"value":4},{"value":5},{"value":6},{"value":7},{"value":8},{"value":9},{"value":10},{"value":11},{"value":12}]}]}],"defaultActions":[{"gotoAndPlay":"Death"}]}]}